is_even/__init__.py
is_even/main.py
is_even_methods-11b0.dist-info/LICENSE
is_even_methods-11b0.dist-info/METADATA
is_even_methods-11b0.dist-info/WHEEL
is_even_methods-11b0.dist-info/top_level.txt
is_even_methods-11b0.dist-info/RECORD
