Metadata-Version: 2.1
Name: is_even_methods
Version: 11b0
Summary: A collection of is_even methods
Home-page: https://github.com/Macosaro/is_even_methods/
License: MIT
License-File: LICENSE
